src/main.py
src/data/__init__.py
src/data/ascii.py
src/data/crypt_file.py
src/data/crypt_key.py
crypt_key-0.0.4.dist-info/METADATA
crypt_key-0.0.4.dist-info/WHEEL
crypt_key-0.0.4.dist-info/entry_points.txt
crypt_key-0.0.4.dist-info/top_level.txt
crypt_key-0.0.4.dist-info/RECORD
