Metadata-Version: 2.4
Name: crypt-key
Version: 0.0.4
Summary: encrypt and decrypt pem-keys and files
Requires-Python: >=3.13
Requires-Dist: pycryptodome
Requires-Dist: rich
Requires-Dist: pyAesCrypt
Requires-Dist: pyfiglet
